dbt/adapters/athena/__init__.py
dbt/adapters/athena/__version__.py
dbt/adapters/athena/column.py
dbt/adapters/athena/config.py
dbt/adapters/athena/connections.py
dbt/adapters/athena/constants.py
dbt/adapters/athena/exceptions.py
dbt/adapters/athena/impl.py
dbt/adapters/athena/lakeformation.py
dbt/adapters/athena/python_submissions.py
dbt/adapters/athena/query_headers.py
dbt/adapters/athena/relation.py
dbt/adapters/athena/s3.py
dbt/adapters/athena/session.py
dbt/adapters/athena/utils.py
dbt/include/athena/__init__.py
dbt/include/athena/dbt_project.yml
dbt/include/athena/profile_template.yml
dbt/include/athena/sample_profiles.yml
dbt/include/athena/macros/adapters/columns.sql
dbt/include/athena/macros/adapters/metadata.sql
dbt/include/athena/macros/adapters/persist_docs.sql
dbt/include/athena/macros/adapters/python_submissions.sql
dbt/include/athena/macros/adapters/relation.sql
dbt/include/athena/macros/adapters/schema.sql
dbt/include/athena/macros/materializations/hooks.sql
dbt/include/athena/macros/materializations/models/helpers/get_partition_batches.sql
dbt/include/athena/macros/materializations/models/helpers/process_bucket_column.sql
dbt/include/athena/macros/materializations/models/incremental/column_helpers.sql
dbt/include/athena/macros/materializations/models/incremental/helpers.sql
dbt/include/athena/macros/materializations/models/incremental/incremental.sql
dbt/include/athena/macros/materializations/models/incremental/merge.sql
dbt/include/athena/macros/materializations/models/incremental/on_schema_change.sql
dbt/include/athena/macros/materializations/models/table/create_table_as.sql
dbt/include/athena/macros/materializations/models/table/table.sql
dbt/include/athena/macros/materializations/models/view/create_or_replace_view.sql
dbt/include/athena/macros/materializations/models/view/create_view_as.sql
dbt/include/athena/macros/materializations/models/view/view.sql
dbt/include/athena/macros/materializations/seeds/helpers.sql
dbt_athena-1.10.0.dist-info/METADATA
dbt_athena-1.10.0.dist-info/WHEEL
dbt_athena-1.10.0.dist-info/licenses/LICENSE
dbt_athena-1.10.0.dist-info/RECORD
